// class version 46.0 (46)
// access flags 0x21
public class me/artspb/pitest/examples/twr/example5/TryWithTwoCloseableExample {

  // compiled from: TryWithTwoCloseableExample.java

  // access flags 0x1
  public <init>()V
   L0
    LINENUMBER 10 L0
    ALOAD 0
    INVOKESPECIAL java/lang/Object.<init> ()V
    RETURN
   L1
    LOCALVARIABLE this Lme/artspb/pitest/examples/twr/example5/TryWithTwoCloseableExample; L0 L1 0
    MAXSTACK = 1
    MAXLOCALS = 1

  // access flags 0x9
  public static main([Ljava/lang/String;)V throws java/io/IOException 
  ATTRIBUTE org.aspectj.weaver.MethodDeclarationLineNumber : unknown
    TRYCATCHBLOCK L0 L1 L2 null
    TRYCATCHBLOCK L3 L4 L5 null
    TRYCATCHBLOCK L6 L7 L7 null
   L8
    LINENUMBER 13 L8
    ACONST_NULL
    ASTORE 1
    ACONST_NULL
    ASTORE 2
   L6
    NEW java/io/ByteArrayOutputStream
    DUP
    INVOKESPECIAL java/io/ByteArrayOutputStream.<init> ()V
    ASTORE 3
   L3
    LINENUMBER 14 L3
    NEW java/io/BufferedOutputStream
    DUP
    ALOAD 3
    INVOKESPECIAL java/io/BufferedOutputStream.<init> (Ljava/io/OutputStream;)V
    ASTORE 4
   L0
    LINENUMBER 15 L0
    ALOAD 4
    INVOKEVIRTUAL java/io/BufferedOutputStream.flush ()V
   L1
    LINENUMBER 16 L1
    ALOAD 4
    IFNULL L4
    ALOAD 4
    INVOKEVIRTUAL java/io/BufferedOutputStream.close ()V
    GOTO L4
   L2
    ASTORE 1
    ALOAD 4
    IFNULL L9
    ALOAD 4
    INVOKEVIRTUAL java/io/BufferedOutputStream.close ()V
   L9
    ALOAD 1
    ATHROW
   L4
    ALOAD 3
    IFNULL L10
    ALOAD 3
    INVOKEVIRTUAL java/io/ByteArrayOutputStream.close ()V
    GOTO L10
   L5
    ASTORE 2
    ALOAD 1
    IFNONNULL L11
    ALOAD 2
    ASTORE 1
    GOTO L12
   L11
    ALOAD 1
    ALOAD 2
    IF_ACMPEQ L12
    ALOAD 1
    ALOAD 2
    INVOKEVIRTUAL java/lang/Throwable.addSuppressed (Ljava/lang/Throwable;)V
   L12
    ALOAD 3
    IFNULL L13
    ALOAD 3
    INVOKEVIRTUAL java/io/ByteArrayOutputStream.close ()V
   L13
    ALOAD 1
    ATHROW
   L7
    ASTORE 2
    ALOAD 1
    IFNONNULL L14
    ALOAD 2
    ASTORE 1
    GOTO L15
   L14
    ALOAD 1
    ALOAD 2
    IF_ACMPEQ L15
    ALOAD 1
    ALOAD 2
    INVOKEVIRTUAL java/lang/Throwable.addSuppressed (Ljava/lang/Throwable;)V
   L15
    ALOAD 1
    ATHROW
   L10
    LINENUMBER 17 L10
    RETURN
   L16
    LOCALVARIABLE args [Ljava/lang/String; L8 L16 0
    LOCALVARIABLE baos Ljava/io/ByteArrayOutputStream; L3 L13 3
    LOCALVARIABLE bos Ljava/io/BufferedOutputStream; L0 L9 4
    MAXSTACK = 3
    MAXLOCALS = 5
}
